cbc_importer/__init__.py
cbc_importer/cli/__init__.py
cbc_importer/cli/connector.py
cbc_importer/cli/wizard.py
cbc_importer/importer.py
cbc_importer/stix_parsers/__init__.py
cbc_importer/stix_parsers/v1/__init__.py
cbc_importer/stix_parsers/v1/object_parsers.py
cbc_importer/stix_parsers/v1/parser.py
cbc_importer/stix_parsers/v2/__init__.py
cbc_importer/stix_parsers/v2/parser.py
cbc_importer/stix_parsers/v2/pattern_parser.py
cbc_importer/taxii_configurator.py
cbc_importer/utils.py
carbon_black_cloud_threat_intelligence_connector-1.10.dist-info/LICENSE
carbon_black_cloud_threat_intelligence_connector-1.10.dist-info/METADATA
carbon_black_cloud_threat_intelligence_connector-1.10.dist-info/WHEEL
carbon_black_cloud_threat_intelligence_connector-1.10.dist-info/entry_points.txt
carbon_black_cloud_threat_intelligence_connector-1.10.dist-info/RECORD
