Metadata-Version: 2.1
Name: carbon-black-cloud-threat-intelligence-connector
Version: 1.10
Summary: Carbon Black Cloud Threat Intelligence Connector
License: BSD-2-Clause
Keywords: connector,carbonblackcloud,stixtaxii,stix,taxii
Author: Dimitar Ganev
Author-email: dimitar.ganev@broadcom.com
Requires-Python: >=3.8,<4.0
Classifier: Intended Audience :: Developers
Classifier: Intended Audience :: System Administrators
Classifier: License :: OSI Approved :: BSD License
Classifier: Operating System :: OS Independent
Classifier: Programming Language :: Python :: 3
Classifier: Programming Language :: Python :: 3.8
Classifier: Programming Language :: Python :: 3.9
Classifier: Programming Language :: Python :: 3.10
Classifier: Programming Language :: Python :: 3.11
Classifier: Programming Language :: Python :: 3.12
Classifier: Programming Language :: Python :: 3 :: Only
Classifier: Topic :: Software Development :: Libraries :: Python Modules
Requires-Dist: arrow (==1.2.2)
Requires-Dist: cabby (==0.1.23)
Requires-Dist: carbon-black-cloud-sdk (==1.3.5)
Requires-Dist: click (==8.0.4)
Requires-Dist: stix (==1.2.0.11)
Requires-Dist: stix-validator (==2.5.1)
Requires-Dist: stix2 (==3.0.1)
Requires-Dist: stix2-patterns (==2.0.0)
Requires-Dist: stix2-validator (==3.0.2)
Requires-Dist: taxii2-client (==2.3.0)
Requires-Dist: typer (==0.4.0)
Requires-Dist: validators (==0.18.2)
